pyshellcli/__init__.py
pyshellcli/bulk_file_rename.py
pyshellcli/config.py
pyshellcli/equations.py
pyshellcli/game.py
pyshellcli/git_commands.py
pyshellcli/graphs.py
pyshellcli/linux_commands.py
pyshellcli/main.py
pyshellcli/ping.py
pyshellcli/shortprompt.py
pyshellcli/song.py
pyshellcli/statistical.py
pyshellcli/stocks.py
pyshellcli/task.py
pyshellcli/terminals.py
pyshellcli/weather.py
pyshellcli/game/BlackJack/accessories.py
pyshellcli/game/BlackJack/main.py
pyshellcli/game/BlackJack/probes.py
pyshellcli/game/Breakout/ball.py
pyshellcli/game/Breakout/main.py
pyshellcli/game/Breakout/paddle.py
pyshellcli/game/Breakout/scoreboard.py
pyshellcli/game/Hangman/main.py
pyshellcli/game/Hangman/words.py
pyshellcli/game/KBC/main.py
pyshellcli/game/KBC/questions.py
pyshellcli/game/Pacman/ghost.py
pyshellcli/game/Pacman/main.py
pyshellcli/game/Pacman/pacman.py
pyshellcli/game/PingPong/ball.py
pyshellcli/game/PingPong/main.py
pyshellcli/game/PingPong/menu.py
pyshellcli/game/PingPong/reflector.py
pyshellcli/game/PingPong/scoretrack.py
pyshellcli/game/PingPong/sound.py
pyshellcli/game/RockPaperScissor/main.py
pyshellcli/game/SnakeGame/food.py
pyshellcli/game/SnakeGame/main.py
pyshellcli/game/SnakeGame/scoreboard.py
pyshellcli/game/SnakeGame/snake.py
pyshellcli/game/TurtleCrossing/TurtleClass.py
pyshellcli/game/TurtleCrossing/main.py
pyshellcli/game/TurtleCrossing/obstacles.py
pyshellcli-1.4.3.dist-info/licenses/LICENSE
pyshellcli-1.4.3.dist-info/METADATA
pyshellcli-1.4.3.dist-info/WHEEL
pyshellcli-1.4.3.dist-info/entry_points.txt
pyshellcli-1.4.3.dist-info/top_level.txt
pyshellcli-1.4.3.dist-info/RECORD
