Metadata-Version: 2.4
Name: pyshellcli
Version: 1.4.3
Summary: PyShell is a lightweight Python-based CLI that enhances the terminal experience with system commands, automation, advance math tools, Artifical Intelligence and network utilities.
Author-email: Ansh Soni <developers.pyshell@gmail.com>
Requires-Python: >=3.7
License-File: LICENSE
Dynamic: license-file
